treetop/__init__.py
treetop-2024.5.13.dev1.dist-info/LICENSE
treetop-2024.5.13.dev1.dist-info/WHEEL
treetop-2024.5.13.dev1.dist-info/METADATA
treetop-2024.5.13.dev1.dist-info/RECORD
