Metadata-Version: 2.1
Name: treetop
Version: 2024.5.13.dev1
Summary: TreeTOP
Keywords: phylogenetic reconstruction,dcm3,iqtree,supertree,phylogeny,biology,bioinformatics
Author: Robert McArthur
Requires-Python: >=3.10,<3.13
Classifier: Development Status :: 1 - Planning
Classifier: Intended Audience :: Science/Research
Classifier: License :: OSI Approved :: BSD License
Classifier: Topic :: Scientific/Engineering :: Bio-Informatics
Classifier: Topic :: Software Development :: Libraries :: Python Modules
Classifier: Operating System :: OS Independent
Classifier: Programming Language :: Python :: 3.10
Classifier: Programming Language :: Python :: 3.11
Classifier: Programming Language :: Python :: 3.12
Requires-Dist: sc-supertree ==2024.5.6
Requires-Dist: cogent3
Requires-Dist: ruff==0.4.4 ; extra == "dev"
Requires-Dist: click==8.1.7 ; extra == "dev"
Requires-Dist: mypy==1.10.0 ; extra == "dev"
Requires-Dist: docformatter ; extra == "dev"
Requires-Dist: flit ; extra == "dev"
Requires-Dist: pytest ; extra == "dev"
Requires-Dist: pytest-cov ; extra == "dev"
Requires-Dist: pytest-xdist ; extra == "dev"
Requires-Dist: nox ; extra == "dev"
Requires-Dist: pytest ; extra == "test"
Requires-Dist: pytest-cov ; extra == "test"
Requires-Dist: pytest-xdist ; extra == "test"
Requires-Dist: nox ; extra == "test"
Project-URL: Bug Tracker, https://github.com/rmcar17/TreeTOP/issues
Project-URL: Source Code, https://github.com/rmcar17/TreeTOP
Provides-Extra: dev
Provides-Extra: test
